{
  "Simple_Json": [
    {
      "id": "EMP_01",
      "First Name": "Sumit Kumar ",
      "Last Name": "Chaudhary",
      "Gender": "Male",
      "Age": "28",
      "Designation": "Software Test Engineer",
      "Experience": "2.6 Years"
    },
    {
      "firstname": "kuldeep",
      "id": "101",
      "age": "12",
      "lastname": "yadav"
    },
    {
      "Designation": "Self Employeed",
      "Experience": "4 Years",
      "First Name": "Sachin",
      "id": "EMP_02",
      "Gender": "Male",
      "Last Name": "Teotiar",
      "Age": "28"
    },
    {
      "Designation": "Self Employeed",
      "Experience": "4 Years",
      "First Name": "Sachin",
      "id": "EMP_04",
      "Gender": "Male",
      "Last Name": "Teotiar",
      "Age": "28"
    },
    {
      "Designation": "Self Employeed",
      "Experience": "4 Years",
      "First Name": "Sachin",
      "id": "EMP_05",
      "Gender": "Male",
      "Last Name": "Teotiar",
      "Age": "28"
    }
  ],
  "ComplexJson": [],
  "Json_Array": []
}